README
setup.py
JsonToMarkdown/__init__.py
JsonToMarkdown/cat.py
JsonToMarkdown/check_obs.py
JsonToMarkdown/json_to_obs.py
JsonToMarkdown/libmd.py
JsonToMarkdown/libsvg.py
JsonToMarkdown/main.py
JsonToMarkdown/preprocess.py
JsonToMarkdown.egg-info/PKG-INFO
JsonToMarkdown.egg-info/SOURCES.txt
JsonToMarkdown.egg-info/dependency_links.txt
JsonToMarkdown.egg-info/entry_points.txt
JsonToMarkdown.egg-info/top_level.txt