Metadata-Version: 1.0
Name: JsonToMarkdown
Version: 1.4.2
Summary: Convert Json to Markdown
Home-page: UNKNOWN
Author: zhaobk
Author-email: zhaobk@nationalchip.com
License: UNKNOWN
Keywords: json markdown
Platform: UNKNOWN
